[{"dirname":"pw2","name":"PW 2","description":"Stats for grades on the PW 2 homework."}, {"dirname":"pw3","name":"PW 3","description":"Stats for grades on the PW 3 homework."}, {"dirname":"pw4","name":"PW 4","description":"Stats for grades on the PW 4 homework."}, {"dirname":"pw5","name":"PW 5","description":"Stats for grades on the PW 5 homework."}, {"dirname":"pw6","name":"PW 6","description":"Stats for grades on the PW 6 homework."}, {"dirname":"pw7","name":"PW 7","description":"Stats for grades on the PW 7 homework."}, {"dirname":"pw8","name":"PW 8","description":"Stats for grades on the PW 8 homework."}, {"dirname":"pwaverage","name":"PW Average","description":"Average stats for grades on all the PW homework."}, {"dirname":"midterm","name":"Midterm","description":"Stats for grades on the midterm exam."}, {"dirname":"final","name":"Final","description":"Stats for grades on the final exam."}, {"dirname":"defense1","name":"Defense 1","description":"Stats for grades on the first defense."}, {"dirname":"defense2","name":"Defense 2","description":"Stats for grades on the second defense."}]